WRFpy-0.2.1.data/scripts/wrfpy
WRFpy-0.2.1.dist-info/METADATA
WRFpy-0.2.1.dist-info/RECORD
WRFpy-0.2.1.dist-info/WHEEL
WRFpy-0.2.1.dist-info/top_level.txt
wrfpy/__init__.py
wrfpy/bumpskin.py
wrfpy/config.py
wrfpy/configuration.py
wrfpy/readObsTemperature.py
wrfpy/scale.py
wrfpy/split_namelist.py
wrfpy/upp.py
wrfpy/utils.py
wrfpy/wps.py
wrfpy/wrf.py
wrfpy/wrfda.py
wrfpy/cylc/archive.py
wrfpy/cylc/combine_synop.py
wrfpy/cylc/copy_synop.py
wrfpy/cylc/prepare_synop.py
wrfpy/cylc/retry_wrf.py
wrfpy/cylc/run_real.py
wrfpy/cylc/run_wrf.py
wrfpy/cylc/upp.py
wrfpy/cylc/wps_init.py
wrfpy/cylc/wps_post.py
wrfpy/cylc/wps_run.py
wrfpy/cylc/wrf_init.py
wrfpy/cylc/wrfda_obs.py
wrfpy/cylc/wrfda_obsproc_init.py
wrfpy/cylc/wrfda_obsproc_run.py
wrfpy/cylc/wrfda_run.py
wrfpy/examples/namelist.wps
wrfpy/scripts/wrfpy
