Metadata-Version: 2.1
Name: WRFpy
Version: 0.2.1
Summary: A python application that provides an easy way to set up, run, and monitor (long) Weather Research and Forecasting  (WRF) simulations.
Home-page: https://github.com/ERA-URBAN/wrfpy
Author: Ronald van Haren
Author-email: r.vanharen@esciencecenter.nl
License: Apache 2.0
Keywords: WRF cylc workflow WRFDA
Platform: UNKNOWN
Classifier: Development Status :: 4 - Beta
Classifier: Topic :: Software Development :: Libraries :: Python Modules
Classifier: License :: OSI Approved :: Apache Software License
Requires-Dist: numpy
Requires-Dist: Jinja2
Requires-Dist: MarkupSafe
Requires-Dist: PyYAML
Requires-Dist: f90nml
